<Objects>
  <Object type="0x5e85" id="Fire Bomb">
    <Enemy />
    <Class>Character</Class>
    <Animation prob="1.0" period="0">
      <Frame time="0.6">
        <Texture>
          <File>lofiEnvironment3</File>
          <Index>0x177</Index>
        </Texture>
      </Frame>
      <Frame time="0.6">
        <Texture>
          <File>lofiEnvironment3</File>
          <Index>0x178</Index>
        </Texture>
      </Frame>
      <Frame time="0.6">
        <Texture>
          <File>lofiEnvironment3</File>
          <Index>0x179</Index>
        </Texture>
      </Frame>
      <Frame time="2.6">
        <Texture>
          <File>lofiEnvironment3</File>
          <Index>0x17b</Index>
        </Texture>
      </Frame>
    </Animation>
    <Texture>
      <File>lofiEnvironment3</File>
      <Index>0x17b</Index>
    </Texture>
    <HitSound>monster/wooden_walls_hit</HitSound>
    <DeathSound>monster/skull_shrine_hit</DeathSound>
    <MaxHitPoints>2000</MaxHitPoints>
    <Defense>30</Defense>
    <XpMult>0</XpMult>
    <Size>100</Size>
    <Projectile id="0">
      <ObjectId>LavaBombBlast</ObjectId>
      <Speed>70</Speed>
      <Damage>130</Damage>
      <Size>140</Size>
      <LifetimeMS>800</LifetimeMS>
      <MultiHit />
    </Projectile>
    <StasisImmune />
    <StunImmune />
  </Object>
  <Object type="0x0dc1" id="Great Snake Egg">
    <Class>Character</Class>
    <Enemy />
    <Size>100</Size>
    <ShadowSize>90</ShadowSize>
    <MaxHitPoints>50</MaxHitPoints>
    <Defense>20</Defense>
    <XpMult>0.0</XpMult>
    <HitSound>monster/wooden_walls_hit</HitSound>
    <DeathSound>monster/stone_walls_death</DeathSound>
    <Texture>
      <File>lofiEnvironment3</File>
      <Index>0x8a</Index>
    </Texture>
    <Animation prob="1.0" period="0.0">
      <Frame time="0.4">
        <Texture>
          <File>lofiEnvironment3</File>
          <Index>0x2f</Index>
        </Texture>
      </Frame>
      <Frame time="0.2">
        <Texture>
          <File>lofiEnvironment3</File>
          <Index>0x36</Index>
        </Texture>
      </Frame>
      <Frame time="0.2">
        <Texture>
          <File>lofiEnvironment3</File>
          <Index>0x37</Index>
        </Texture>
      </Frame>
      <Frame time="0.2">
        <Texture>
          <File>lofiEnvironment3</File>
          <Index>0x36</Index>
        </Texture>
      </Frame>
    </Animation>
  </Object>
  <Object type="0x1705" id="Coral Gift">
    <Group>Ocean Trench</Group>
    <Class>Character</Class>
    <StasisImmune />
    <Enemy />
    <NoMiniMap />
    <MaxHitPoints>1200</MaxHitPoints>
    <XpMult>0.0</XpMult>
    <Size>90</Size>
    <Defense>5</Defense>
    <Texture>
      <File>lofiEnvironment3</File>
      <Index>0x22</Index>
    </Texture>
    <AltTexture id="1">
      <Texture>
        <File>lofiEnvironment3</File>
        <Index>0x23</Index>
      </Texture>
    </AltTexture>
    <AltTexture id="2">
      <Texture>
        <File>lofiEnvironment3</File>
        <Index>0x24</Index>
      </Texture>
    </AltTexture>
    <HitSound>monster/djinn_hit</HitSound>
    <DeathSound>monster/flaming_skulls_death</DeathSound>
  </Object>
  <Object type="0x0d86" id="Quiet Bomb">
    <Group>Oryx's Minions</Group>
    <Class>Character</Class>
    <StasisImmune />
    <Enemy />
    <NoMiniMap />
    <MaxHitPoints>100</MaxHitPoints>
    <XpMult>0.0</XpMult>
    <Size>90</Size>
    <Defense>0</Defense>
    <Texture>
      <File>lofiEnvironment3</File>
      <Index>0x22</Index>
    </Texture>
    <AltTexture id="1">
      <Texture>
        <File>lofiEnvironment3</File>
        <Index>0x23</Index>
      </Texture>
    </AltTexture>
    <AltTexture id="2">
      <Texture>
        <File>lofiEnvironment3</File>
        <Index>0x24</Index>
      </Texture>
    </AltTexture>
    <HitSound>monster/skeletons_hit</HitSound>
    <DeathSound>monster/skull_shrine_hit</DeathSound>
    <Projectile id="0">
      <ObjectId>Mute Spell</ObjectId>
      <Speed>50</Speed>
      <MinDamage>10</MinDamage>
      <MaxDamage>20</MaxDamage>
      <Size>80</Size>
      <LifetimeMS>1000</LifetimeMS>
      <ConditionEffect duration="5">Quiet</ConditionEffect>
      <MultiHit />
    </Projectile>
  </Object>
  <Object type="0x0df0" id="Purple Goo">
    <Enemy />
    <Class>Character</Class>
    <RandomTexture>
      <Texture>
        <File>lofiEnvironment3</File>
        <Index>0x85</Index>
      </Texture>
      <Texture>
        <File>lofiEnvironment3</File>
        <Index>0x86</Index>
      </Texture>
      <Texture>
        <File>lofiEnvironment3</File>
        <Index>0x87</Index>
      </Texture>
      <Texture>
        <File>lofiEnvironment3</File>
        <Index>0x88</Index>
      </Texture>
      <Texture>
        <File>lofiEnvironment3</File>
        <Index>0x89</Index>
      </Texture>
    </RandomTexture>
    <Size>90</Size>
    <ShadowSize>0</ShadowSize>
    <DrawUnder />
    <NoMiniMap />
    <MaxHitPoints>2000</MaxHitPoints>
    <Defense>0</Defense>
    <XpMult>0</XpMult>
    <Projectile id="0">
      <ObjectId>Invisible</ObjectId>
      <MinDamage>40</MinDamage>
      <MaxDamage>70</MaxDamage>
      <Speed>0</Speed>
      <Size>85</Size>
      <LifetimeMS>6000</LifetimeMS>
      <MultiHit />
      <ConditionEffect duration="5">Sick</ConditionEffect>
      <ConditionEffect duration="3.4">Slowed</ConditionEffect>
    </Projectile>
  </Object>
  <Object type="0x1652" id="Dreidel">
    <DisplayId>Dreidel</DisplayId>
    <Class>Character</Class>
    <Texture>
      <File>lofiEnvironment3</File>
      <Index>0xf4</Index>
    </Texture>
    <Animation prob="1.0" period="0.4">
      <Frame time="0.1">
        <Texture>
          <File>lofiEnvironment3</File>
          <Index>0xf4</Index>
        </Texture>
      </Frame>
      <Frame time="0.1">
        <Texture>
          <File>lofiEnvironment3</File>
          <Index>0xf5</Index>
        </Texture>
      </Frame>
      <Frame time="0.1">
        <Texture>
          <File>lofiEnvironment3</File>
          <Index>0xf6</Index>
        </Texture>
      </Frame>
      <Frame time="0.1">
        <Texture>
          <File>lofiEnvironment3</File>
          <Index>0xf7</Index>
        </Texture>
      </Frame>
    </Animation>
    <NoMiniMap />
    <Size>60</Size>
    <ShadowSize>60</ShadowSize>
  </Object>
</Objects>