<Objects>
  <Object type="0xa5c" id="Robe of the Neophyte">
    <Class>Equipment</Class>
    <Item />
    <Texture>
      <File>lofiObj5</File>
      <Index>0x10</Index>
    </Texture>
    <SlotType>14</SlotType>
    <Tier>1</Tier>
    <Description>A long woolen robe favored by students of magic.</Description>
    <ActivateOnEquip stat="21" amount="2">IncrementStat</ActivateOnEquip>
    <BagType>1</BagType>
    <feedPower>7</feedPower>
  </Object>
  <Object type="0xa7e" id="Robe of the Apprentice">
    <Class>Equipment</Class>
    <Item />
    <Texture>
      <File>lofiObj5</File>
      <Index>0x11</Index>
    </Texture>
    <SlotType>14</SlotType>
    <Tier>2</Tier>
    <Description>A robe woven of rare yellow silk.</Description>
    <ActivateOnEquip stat="21" amount="3">IncrementStat</ActivateOnEquip>
    <ActivateOnEquip stat="27" amount="1">IncrementStat</ActivateOnEquip>
    <BagType>1</BagType>
    <feedPower>9</feedPower>
  </Object>
  <Object type="0xa5d" id="Robe of the Acolyte">
    <Class>Equipment</Class>
    <Item />
    <Texture>
      <File>lofiObj5</File>
      <Index>0x12</Index>
    </Texture>
    <SlotType>14</SlotType>
    <Tier>3</Tier>
    <Description>A well-made robe of enchanted blue silk.</Description>
    <ActivateOnEquip stat="21" amount="4">IncrementStat</ActivateOnEquip>
    <ActivateOnEquip stat="27" amount="1">IncrementStat</ActivateOnEquip>
    <ActivateOnEquip stat="3" amount="10">IncrementStat</ActivateOnEquip>
    <BagType>1</BagType>
    <feedPower>14</feedPower>
  </Object>
  <Object type="0xa7f" id="Robe of the Student">
    <Class>Equipment</Class>
    <Item />
    <Texture>
      <File>lofiObj5</File>
      <Index>0x13</Index>
    </Texture>
    <SlotType>14</SlotType>
    <Tier>4</Tier>
    <Description>A magical robe of faintly glowing wizardcloth.</Description>
    <ActivateOnEquip stat="21" amount="4">IncrementStat</ActivateOnEquip>
    <ActivateOnEquip stat="27" amount="2">IncrementStat</ActivateOnEquip>
    <ActivateOnEquip stat="3" amount="15">IncrementStat</ActivateOnEquip>
    <BagType>1</BagType>
    <feedPower>20</feedPower>
  </Object>
  <Object type="0xa80" id="Robe of the Conjurer">
    <Class>Equipment</Class>
    <Item />
    <Texture>
      <File>lofiObj5</File>
      <Index>0x14</Index>
    </Texture>
    <SlotType>14</SlotType>
    <Tier>5</Tier>
    <Description>A magical robe of grey moonsilk.</Description>
    <ActivateOnEquip stat="21" amount="6">IncrementStat</ActivateOnEquip>
    <ActivateOnEquip stat="27" amount="2">IncrementStat</ActivateOnEquip>
    <ActivateOnEquip stat="3" amount="20">IncrementStat</ActivateOnEquip>
    <BagType>1</BagType>
    <feedPower>27</feedPower>
  </Object>
  <Object type="0xa5e" id="Robe of the Adept">
    <Class>Equipment</Class>
    <Item />
    <Texture>
      <File>lofiObj5</File>
      <Index>0x15</Index>
    </Texture>
    <SlotType>14</SlotType>
    <Tier>6</Tier>
    <Description>An enchanted robe of dark moonweave.</Description>
    <ActivateOnEquip stat="21" amount="7">IncrementStat</ActivateOnEquip>
    <ActivateOnEquip stat="27" amount="3">IncrementStat</ActivateOnEquip>
    <ActivateOnEquip stat="3" amount="25">IncrementStat</ActivateOnEquip>
    <BagType>1</BagType>
    <feedPower>39</feedPower>
  </Object>
  <Object type="0xa5f" id="Robe of the Invoker">
    <Class>Equipment</Class>
    <Item />
    <Texture>
      <File>lofiObj5</File>
      <Index>0x16</Index>
    </Texture>
    <SlotType>14</SlotType>
    <Tier>7</Tier>
    <Description>A powerful robe of delicately embroidered red feythread.</Description>
    <ActivateOnEquip stat="21" amount="8">IncrementStat</ActivateOnEquip>
    <ActivateOnEquip stat="27" amount="3">IncrementStat</ActivateOnEquip>
    <ActivateOnEquip stat="3" amount="30">IncrementStat</ActivateOnEquip>
    <BagType>2</BagType>
    <feedPower>55</feedPower>
  </Object>
  <Object type="0xadc" id="Robe of the Illusionist">
    <Class>Equipment</Class>
    <Item />
    <Texture>
      <File>lofiObj5</File>
      <Index>0x17</Index>
    </Texture>
    <SlotType>14</SlotType>
    <Tier>8</Tier>
    <Description>A silversilk robe masterfully sewn with morningdew spider threads.</Description>
    <ActivateOnEquip stat="20" amount="1">IncrementStat</ActivateOnEquip>
    <ActivateOnEquip stat="21" amount="8">IncrementStat</ActivateOnEquip>
    <ActivateOnEquip stat="27" amount="4">IncrementStat</ActivateOnEquip>
    <ActivateOnEquip stat="3" amount="35">IncrementStat</ActivateOnEquip>
    <BagType>2</BagType>
    <FameBonus>1</FameBonus>
    <feedPower>77</feedPower>
  </Object>
  <Object type="0xa60" id="Robe of the Master">
    <Class>Equipment</Class>
    <Item />
    <Texture>
      <File>lofiObj5</File>
      <Index>0x18</Index>
    </Texture>
    <SlotType>14</SlotType>
    <Tier>9</Tier>
    <Description>A beautiful and versatile robe of the lightest magethread.</Description>
    <ActivateOnEquip stat="20" amount="2">IncrementStat</ActivateOnEquip>
    <ActivateOnEquip stat="21" amount="9">IncrementStat</ActivateOnEquip>
    <ActivateOnEquip stat="27" amount="5">IncrementStat</ActivateOnEquip>
    <ActivateOnEquip stat="3" amount="40">IncrementStat</ActivateOnEquip>
    <BagType>2</BagType>
    <FameBonus>1</FameBonus>
    <feedPower>110</feedPower>
  </Object>
  <Object type="0xa94" id="Robe of the Shadow Magus">
    <Class>Equipment</Class>
    <Item />
    <Texture>
      <File>lofiObj5</File>
      <Index>0x19</Index>
    </Texture>
    <SlotType>14</SlotType>
    <Tier>10</Tier>
    <Description>A highly decorated robe of purple wizardcloth, imbued with powers of sorcery and darkness.</Description>
    <ActivateOnEquip stat="20" amount="2">IncrementStat</ActivateOnEquip>
    <ActivateOnEquip stat="21" amount="10">IncrementStat</ActivateOnEquip>
    <ActivateOnEquip stat="27" amount="5">IncrementStat</ActivateOnEquip>
    <ActivateOnEquip stat="3" amount="45">IncrementStat</ActivateOnEquip>
    <BagType>4</BagType>
    <FameBonus>2</FameBonus>
    <feedPower>155</feedPower>
  </Object>
  <Object type="0xa95" id="Robe of the Moon Wizard">
    <Class>Equipment</Class>
    <Item />
    <Texture>
      <File>lofiObj5</File>
      <Index>0x1a</Index>
    </Texture>
    <SlotType>14</SlotType>
    <Tier>11</Tier>
    <Description>A robe of rarest moonsilk, enhanced long ago with deep nocturnal enchantments.</Description>
    <ActivateOnEquip stat="20" amount="3">IncrementStat</ActivateOnEquip>
    <ActivateOnEquip stat="21" amount="11">IncrementStat</ActivateOnEquip>
    <ActivateOnEquip stat="27" amount="6">IncrementStat</ActivateOnEquip>
    <ActivateOnEquip stat="3" amount="50">IncrementStat</ActivateOnEquip>
    <BagType>4</BagType>
    <FameBonus>3</FameBonus>
    <feedPower>218</feedPower>
  </Object>
  <Object type="0xa96" id="Robe of the Elder Warlock">
    <Class>Equipment</Class>
    <Item />
    <Texture>
      <File>lofiObj5</File>
      <Index>0x1b</Index>
    </Texture>
    <SlotType>14</SlotType>
    <Tier>12</Tier>
    <Description>A brightly colored robe of metallic threads, woven in the ancient elvish style and steeped in fey auras.</Description>
    <ActivateOnEquip stat="20" amount="3">IncrementStat</ActivateOnEquip>
    <ActivateOnEquip stat="21" amount="12">IncrementStat</ActivateOnEquip>
    <ActivateOnEquip stat="27" amount="6">IncrementStat</ActivateOnEquip>
    <ActivateOnEquip stat="3" amount="50">IncrementStat</ActivateOnEquip>
    <BagType>4</BagType>
    <FameBonus>4</FameBonus>
    <feedPower>308</feedPower>
  </Object>
  <Object type="0xb05" id="Robe of the Grand Sorcerer">
    <Class>Equipment</Class>
    <Item />
    <Texture>
      <File>lofiObj5</File>
      <Index>0x1c</Index>
    </Texture>
    <SlotType>14</SlotType>
    <Tier>13</Tier>
    <Description>A bloodweft robe adorned with rubies and firegarnets, worn by an ancient sect of masterful wizards.</Description>
    <ActivateOnEquip stat="20" amount="4">IncrementStat</ActivateOnEquip>
    <ActivateOnEquip stat="21" amount="13">IncrementStat</ActivateOnEquip>
    <ActivateOnEquip stat="27" amount="6">IncrementStat</ActivateOnEquip>
    <ActivateOnEquip stat="3" amount="55">IncrementStat</ActivateOnEquip>
    <BagType>4</BagType>
    <FameBonus>4</FameBonus>
    <feedPower>435</feedPower>
  </Object>
  <Object type="0x9cf" id="Robe of the Star Mother">
    <Class>Equipment</Class>
    <Item />
    <Tier>14</Tier>
    <Texture>
      <File>lofiObj5</File>
      <Index>0x1d</Index>
    </Texture>
    <SlotType>14</SlotType>
    <Description>A robe of gossamer glowthread, used by the sorceress matriarchs of the western kingdoms.</Description>
    <ActivateOnEquip stat="20" amount="4">IncrementStat</ActivateOnEquip>
    <ActivateOnEquip stat="21" amount="14">IncrementStat</ActivateOnEquip>
    <ActivateOnEquip stat="27" amount="7">IncrementStat</ActivateOnEquip>
    <ActivateOnEquip stat="3" amount="60">IncrementStat</ActivateOnEquip>
    <BagType>4</BagType>
    <FameBonus>5</FameBonus>
    <feedPower>0</feedPower>
  </Object>
  <Object type="0x9d0" id="Robe of the Ancient Intellect">
    <Class>Equipment</Class>
    <Item />
    <Tier>15</Tier>
    <Texture>
      <File>lofiObj5</File>
      <Index>0x1e</Index>
    </Texture>
    <SlotType>14</SlotType>
    <Description>A phenomenal robe magically woven from fibers of sapphire, topaz and lapis lazuli, created for the archwizard of the seraphic realms.</Description>
    <ActivateOnEquip stat="20" amount="4">IncrementStat</ActivateOnEquip>
    <ActivateOnEquip stat="21" amount="15">IncrementStat</ActivateOnEquip>
    <ActivateOnEquip stat="27" amount="7">IncrementStat</ActivateOnEquip>
    <ActivateOnEquip stat="3" amount="65">IncrementStat</ActivateOnEquip>
    <BagType>4</BagType>
    <FameBonus>6</FameBonus>
    <feedPower>0</feedPower>
  </Object>
</Objects>